calmutils/__init__.py
calmutils/color/__init__.py
calmutils/color/color.py
calmutils/descriptors/__init__.py
calmutils/descriptors/geometric_local_descriptors.py
calmutils/descriptors/matching.py
calmutils/filter/__init__.py
calmutils/filter/bandpass.py
calmutils/imageio/__init__.py
calmutils/imageio/bf.py
calmutils/imageio/imspector_msr.py
calmutils/imageio/multipage_tiff.py
calmutils/imageio/pims_msr.py
calmutils/imageio/tiff_imagej.py
calmutils/imageio/nd2_helpers/__init__.py
calmutils/imageio/nd2_helpers/nd2_metadata_helpers.py
calmutils/localization/__init__.py
calmutils/localization/dog.py
calmutils/localization/functions.py
calmutils/localization/gaussian_fit.py
calmutils/localization/multi_gaussian_fit.py
calmutils/localization/quadratic.py
calmutils/localization/radial_symmetry.py
calmutils/localization/metrics/__init__.py
calmutils/localization/metrics/localization_metrics.py
calmutils/localization/multiview/__init__.py
calmutils/localization/multiview/multi_cut_fit.py
calmutils/localization/util/__init__.py
calmutils/localization/util/ellipse_plot.py
calmutils/misc/__init__.py
calmutils/misc/bounding_boxes.py
calmutils/misc/dict_utils.py
calmutils/misc/file_utils.py
calmutils/misc/rprops.py
calmutils/misc/selections.py
calmutils/misc/sort_utils.py
calmutils/misc/string_utils.py
calmutils/misc/json/__init__.py
calmutils/misc/json/json_helpers.py
calmutils/misc/visualization/__init__.py
calmutils/misc/visualization/projections.py
calmutils/morphology/__init__.py
calmutils/morphology/directed_dist.py
calmutils/morphology/mask_postprocessing.py
calmutils/morphology/structuring_elements.py
calmutils/segmentation/__init__.py
calmutils/segmentation/label_merging.py
calmutils/segmentation/mask_tiling.py
calmutils/simulation/__init__.py
calmutils/simulation/sim_util.py
calmutils/stitching/__init__.py
calmutils/stitching/phase_correlation.py
calmutils/stitching/registration.py
calmutils/stitching/stitching.py
calmutils/stitching/tiling.py
calmutils-0.1.5.dist-info/METADATA
calmutils-0.1.5.dist-info/WHEEL
calmutils-0.1.5.dist-info/RECORD
