Metadata-Version: 2.4
Name: CalmUtils
Version: 0.1.5
Summary: Commonly used Python code at the Center for Advanced Light Microscopy
Project-URL: Homepage, https://github.com/CALM-LMU/CalmUtils
Project-URL: Bug Tracker, https://github.com/CALM-LMU/CalmUtils/issues
Author-email: David Hoerl <hoerl@bio.lmu.de>
Requires-Dist: fastremap
Requires-Dist: matplotlib
Requires-Dist: nd2
Requires-Dist: numba
Requires-Dist: numpy
Requires-Dist: scikit-image
Requires-Dist: scipy
Requires-Dist: tqdm
